alphaavatar/plugins/character/__init__.py
alphaavatar/plugins/character/enum.py
alphaavatar/plugins/character/log.py
alphaavatar/plugins/character/version.py
alphaavatar/plugins/character/airi_avatar/__init__.py
alphaavatar/plugins/character/airi_avatar/check.py
alphaavatar/plugins/character/airi_avatar/config.py
alphaavatar/plugins/character/airi_avatar/install.py
alphaavatar/plugins/character/airi_avatar/runner.py
alphaavatar/plugins/character/airi_avatar/session.py
alpha_avatar_plugins_character-0.4.0.dist-info/METADATA
alpha_avatar_plugins_character-0.4.0.dist-info/WHEEL
alpha_avatar_plugins_character-0.4.0.dist-info/entry_points.txt
alpha_avatar_plugins_character-0.4.0.dist-info/RECORD
